{
  "id": "7e11ceb0-42ce-4f20-b106-09988f094e8e",
  "prevId": "00000000-0000-0000-0000-000000000000",
  "version": "7",
  "dialect": "postgresql",
  "tables": {
    "public.generated_letters": {
      "name": "generated_letters",
      "schema": "",
      "columns": {
        "id": {
          "name": "id",
          "type": "text",
          "primaryKey": true,
          "notNull": true
        },
        "submission_id": {
          "name": "submission_id",
          "type": "text",
          "primaryKey": false,
          "notNull": true
        },
        "letter_number": {
          "name": "letter_number",
          "type": "varchar(100)",
          "primaryKey": false,
          "notNull": true
        },
        "file_name": {
          "name": "file_name",
          "type": "varchar(255)",
          "primaryKey": false,
          "notNull": true
        },
        "file_url": {
          "name": "file_url",
          "type": "text",
          "primaryKey": false,
          "notNull": true
        },
        "file_type": {
          "name": "file_type",
          "type": "varchar(10)",
          "primaryKey": false,
          "notNull": true
        },
        "generated_by": {
          "name": "generated_by",
          "type": "text",
          "primaryKey": false,
          "notNull": true
        },
        "generated_at": {
          "name": "generated_at",
          "type": "timestamp",
          "primaryKey": false,
          "notNull": true,
          "default": "now()"
        },
        "created_at": {
          "name": "created_at",
          "type": "timestamp",
          "primaryKey": false,
          "notNull": true,
          "default": "now()"
        }
      },
      "indexes": {},
      "foreignKeys": {
        "generated_letters_submission_id_submissions_id_fk": {
          "name": "generated_letters_submission_id_submissions_id_fk",
          "tableFrom": "generated_letters",
          "tableTo": "submissions",
          "columnsFrom": [
            "submission_id"
          ],
          "columnsTo": [
            "id"
          ],
          "onDelete": "cascade",
          "onUpdate": "no action"
        }
      },
      "compositePrimaryKeys": {},
      "uniqueConstraints": {
        "generated_letters_letter_number_unique": {
          "name": "generated_letters_letter_number_unique",
          "nullsNotDistinct": false,
          "columns": [
            "letter_number"
          ]
        }
      },
      "policies": {},
      "checkConstraints": {},
      "isRLSEnabled": false
    },
    "public.submission_documents": {
      "name": "submission_documents",
      "schema": "",
      "columns": {
        "id": {
          "name": "id",
          "type": "text",
          "primaryKey": true,
          "notNull": true
        },
        "submission_id": {
          "name": "submission_id",
          "type": "text",
          "primaryKey": false,
          "notNull": true
        },
        "file_name": {
          "name": "file_name",
          "type": "varchar(255)",
          "primaryKey": false,
          "notNull": true
        },
        "original_name": {
          "name": "original_name",
          "type": "varchar(255)",
          "primaryKey": false,
          "notNull": true
        },
        "file_type": {
          "name": "file_type",
          "type": "varchar(50)",
          "primaryKey": false,
          "notNull": true
        },
        "file_size": {
          "name": "file_size",
          "type": "integer",
          "primaryKey": false,
          "notNull": true
        },
        "file_url": {
          "name": "file_url",
          "type": "text",
          "primaryKey": false,
          "notNull": true
        },
        "document_type": {
          "name": "document_type",
          "type": "document_type",
          "typeSchema": "public",
          "primaryKey": false,
          "notNull": true
        },
        "uploaded_by": {
          "name": "uploaded_by",
          "type": "text",
          "primaryKey": false,
          "notNull": true
        },
        "created_at": {
          "name": "created_at",
          "type": "timestamp",
          "primaryKey": false,
          "notNull": true,
          "default": "now()"
        }
      },
      "indexes": {},
      "foreignKeys": {
        "submission_documents_submission_id_submissions_id_fk": {
          "name": "submission_documents_submission_id_submissions_id_fk",
          "tableFrom": "submission_documents",
          "tableTo": "submissions",
          "columnsFrom": [
            "submission_id"
          ],
          "columnsTo": [
            "id"
          ],
          "onDelete": "cascade",
          "onUpdate": "no action"
        }
      },
      "compositePrimaryKeys": {},
      "uniqueConstraints": {},
      "policies": {},
      "checkConstraints": {},
      "isRLSEnabled": false
    },
    "public.submissions": {
      "name": "submissions",
      "schema": "",
      "columns": {
        "id": {
          "name": "id",
          "type": "text",
          "primaryKey": true,
          "notNull": true
        },
        "team_id": {
          "name": "team_id",
          "type": "text",
          "primaryKey": false,
          "notNull": true
        },
        "company_name": {
          "name": "company_name",
          "type": "varchar(255)",
          "primaryKey": false,
          "notNull": true
        },
        "company_address": {
          "name": "company_address",
          "type": "text",
          "primaryKey": false,
          "notNull": true
        },
        "company_phone": {
          "name": "company_phone",
          "type": "varchar(50)",
          "primaryKey": false,
          "notNull": false
        },
        "company_email": {
          "name": "company_email",
          "type": "varchar(255)",
          "primaryKey": false,
          "notNull": false
        },
        "company_supervisor": {
          "name": "company_supervisor",
          "type": "varchar(255)",
          "primaryKey": false,
          "notNull": false
        },
        "position": {
          "name": "position",
          "type": "varchar(255)",
          "primaryKey": false,
          "notNull": false
        },
        "start_date": {
          "name": "start_date",
          "type": "timestamp",
          "primaryKey": false,
          "notNull": false
        },
        "end_date": {
          "name": "end_date",
          "type": "timestamp",
          "primaryKey": false,
          "notNull": false
        },
        "description": {
          "name": "description",
          "type": "text",
          "primaryKey": false,
          "notNull": false
        },
        "status": {
          "name": "status",
          "type": "submission_status",
          "typeSchema": "public",
          "primaryKey": false,
          "notNull": true,
          "default": "'DRAFT'"
        },
        "rejection_reason": {
          "name": "rejection_reason",
          "type": "text",
          "primaryKey": false,
          "notNull": false
        },
        "approved_by": {
          "name": "approved_by",
          "type": "text",
          "primaryKey": false,
          "notNull": false
        },
        "approved_at": {
          "name": "approved_at",
          "type": "timestamp",
          "primaryKey": false,
          "notNull": false
        },
        "submitted_at": {
          "name": "submitted_at",
          "type": "timestamp",
          "primaryKey": false,
          "notNull": false
        },
        "created_at": {
          "name": "created_at",
          "type": "timestamp",
          "primaryKey": false,
          "notNull": true,
          "default": "now()"
        },
        "updated_at": {
          "name": "updated_at",
          "type": "timestamp",
          "primaryKey": false,
          "notNull": true,
          "default": "now()"
        }
      },
      "indexes": {},
      "foreignKeys": {
        "submissions_team_id_teams_id_fk": {
          "name": "submissions_team_id_teams_id_fk",
          "tableFrom": "submissions",
          "tableTo": "teams",
          "columnsFrom": [
            "team_id"
          ],
          "columnsTo": [
            "id"
          ],
          "onDelete": "cascade",
          "onUpdate": "no action"
        }
      },
      "compositePrimaryKeys": {},
      "uniqueConstraints": {},
      "policies": {},
      "checkConstraints": {},
      "isRLSEnabled": false
    },
    "public.team_members": {
      "name": "team_members",
      "schema": "",
      "columns": {
        "id": {
          "name": "id",
          "type": "text",
          "primaryKey": true,
          "notNull": true
        },
        "team_id": {
          "name": "team_id",
          "type": "text",
          "primaryKey": false,
          "notNull": true
        },
        "user_id": {
          "name": "user_id",
          "type": "text",
          "primaryKey": false,
          "notNull": true
        },
        "invitation_status": {
          "name": "invitation_status",
          "type": "invitation_status",
          "typeSchema": "public",
          "primaryKey": false,
          "notNull": true,
          "default": "'PENDING'"
        },
        "invited_at": {
          "name": "invited_at",
          "type": "timestamp",
          "primaryKey": false,
          "notNull": true,
          "default": "now()"
        },
        "responded_at": {
          "name": "responded_at",
          "type": "timestamp",
          "primaryKey": false,
          "notNull": false
        },
        "invited_by": {
          "name": "invited_by",
          "type": "text",
          "primaryKey": false,
          "notNull": false
        }
      },
      "indexes": {},
      "foreignKeys": {
        "team_members_team_id_teams_id_fk": {
          "name": "team_members_team_id_teams_id_fk",
          "tableFrom": "team_members",
          "tableTo": "teams",
          "columnsFrom": [
            "team_id"
          ],
          "columnsTo": [
            "id"
          ],
          "onDelete": "cascade",
          "onUpdate": "no action"
        }
      },
      "compositePrimaryKeys": {},
      "uniqueConstraints": {},
      "policies": {},
      "checkConstraints": {},
      "isRLSEnabled": false
    },
    "public.teams": {
      "name": "teams",
      "schema": "",
      "columns": {
        "id": {
          "name": "id",
          "type": "text",
          "primaryKey": true,
          "notNull": true
        },
        "code": {
          "name": "code",
          "type": "varchar(50)",
          "primaryKey": false,
          "notNull": true
        },
        "leader_id": {
          "name": "leader_id",
          "type": "text",
          "primaryKey": false,
          "notNull": true
        },
        "status": {
          "name": "status",
          "type": "team_status",
          "typeSchema": "public",
          "primaryKey": false,
          "notNull": true,
          "default": "'PENDING'"
        }
      },
      "indexes": {},
      "foreignKeys": {},
      "compositePrimaryKeys": {},
      "uniqueConstraints": {
        "teams_code_unique": {
          "name": "teams_code_unique",
          "nullsNotDistinct": false,
          "columns": [
            "code"
          ]
        }
      },
      "policies": {},
      "checkConstraints": {},
      "isRLSEnabled": false
    }
  },
  "enums": {
    "public.document_type": {
      "name": "document_type",
      "schema": "public",
      "values": [
        "KTP",
        "TRANSKRIP",
        "KRS",
        "PROPOSAL",
        "OTHER"
      ]
    },
    "public.invitation_status": {
      "name": "invitation_status",
      "schema": "public",
      "values": [
        "PENDING",
        "ACCEPTED",
        "REJECTED"
      ]
    },
    "public.submission_status": {
      "name": "submission_status",
      "schema": "public",
      "values": [
        "DRAFT",
        "MENUNGGU",
        "DITOLAK",
        "DITERIMA"
      ]
    },
    "public.team_status": {
      "name": "team_status",
      "schema": "public",
      "values": [
        "PENDING",
        "FIXED"
      ]
    }
  },
  "schemas": {},
  "sequences": {},
  "roles": {},
  "policies": {},
  "views": {},
  "_meta": {
    "columns": {},
    "schemas": {},
    "tables": {}
  }
}